{
    "env": {
        "defaultConfigurationProvider": "ms-vscode.cmake-tools"
    },
    "configurations": [
        {
            "name": "Linux",
            "configurationProvider": "${defaultConfigurationProvider}",
            "compileCommands": "${workspaceFolder}/.vscode/compile_commands.json",
            "browse": {
                "path": [
                    "${workspaceFolder}"
                ],
                "limitSymbolsToIncludedHeaders": true,
                "databaseFilename": ""
            }
        }
    ],
    "version": 4
}